shared_secret_authenticator.py
shared_secret_authenticator-2.0.1.dist-info/LICENSE
shared_secret_authenticator-2.0.1.dist-info/METADATA
shared_secret_authenticator-2.0.1.dist-info/WHEEL
shared_secret_authenticator-2.0.1.dist-info/top_level.txt
shared_secret_authenticator-2.0.1.dist-info/zip-safe
shared_secret_authenticator-2.0.1.dist-info/RECORD
